speechmix/__init__.py
speechmix/hf_model.py
speechmix/model.py
test/__init__.py
test/test_hf_model.py
test/test_model.py
test/test_train.py
speechmix-0.0.32.dist-info/METADATA
speechmix-0.0.32.dist-info/WHEEL
speechmix-0.0.32.dist-info/top_level.txt
speechmix-0.0.32.dist-info/RECORD
