Metadata-Version: 2.1
Name: speechmix
Version: 0.0.32
Summary: Explore different way to mix speech model(wav2vec2, hubert) and nlp model(BART,T5,GPT) together
Home-page: https://github.com/voidful/SpeechMix
Author: Voidful
Author-email: voidful.stack@gmail.com
License: Apache
Keywords: transformer huggingface nlp speech
Platform: UNKNOWN
Classifier: Development Status :: 4 - Beta
Classifier: Intended Audience :: Science/Research
Classifier: Topic :: Scientific/Engineering :: Artificial Intelligence
Classifier: License :: OSI Approved :: Apache Software License
Classifier: Programming Language :: Python :: 3.6
Requires-Python: >=3.5.0
Requires-Dist: asrp
Requires-Dist: transformers (>=4.12.3)
Requires-Dist: datasets (>=1.15.1)
Requires-Dist: librosa
Requires-Dist: s3prl
